	<sequences>
		<sequence
			name="EnemyWavesInner1"
			wizard=""
			script="CurrentMap/sequences/seq0.vs">
		</sequence>
		<sequence
			name="Main"
			wizard=""
			script="CurrentMap/sequences/seq1.vs">
		</sequence>
		<sequence
			name="EnemyWavesInner2"
			wizard=""
			script="CurrentMap/sequences/seq2.vs">
		</sequence>
		<sequence
			name="EnemyWavesOuter1"
			wizard=""
			script="CurrentMap/sequences/seq3.vs">
		</sequence>
		<sequence
			name="EnemyWavesOuter2"
			wizard=""
			script="CurrentMap/sequences/seq4.vs">
		</sequence>
		<sequence
			name="Lose"
			wizard=""
			script="CurrentMap/sequences/seq5.vs">
		</sequence>
		<sequence
			name="EnemyWavesOuter3"
			wizard=""
			script="CurrentMap/sequences/seq6.vs">
		</sequence>
		<sequence
			name="Win"
			wizard=""
			script="CurrentMap/sequences/seq7.vs">
		</sequence>
		<sequence
			name="RearAttack"
			wizard=""
			script="CurrentMap/sequences/seq8.vs">
		</sequence>
		<sequence
			name="Event1"
			wizard=""
			script="CurrentMap/sequences/seq9.vs">
		</sequence>
		<sequence
			name="MountaineersGuard"
			wizard=""
			script="CurrentMap/sequences/seq10.vs">
		</sequence>
		<sequence
			name="SmallTownDefence"
			wizard=""
			script="CurrentMap/sequences/seq11.vs">
		</sequence>
		<sequence
			name="VillagesTribute"
			wizard=""
			script="CurrentMap/sequences/seq14.vs">
		</sequence>
		<sequence
			name="Event2"
			wizard=""
			script="CurrentMap/sequences/seq16.vs">
		</sequence>
		<sequence
			name="RomeReinforcements"
			wizard=""
			script="CurrentMap/sequences/seq18.vs">
		</sequence>
		<sequence
			name="Event3"
			wizard=""
			script="CurrentMap/sequences/seq19.vs">
		</sequence>
		<sequence
			name="Event4"
			wizard=""
			script="CurrentMap/sequences/seq20.vs">
		</sequence>
		<sequence
			name="Event6"
			wizard=""
			script="CurrentMap/sequences/seq21.vs">
		</sequence>
		<sequence
			name="Event5"
			wizard=""
			script="CurrentMap/sequences/seq22.vs">
		</sequence>
		<sequence
			name="Bonuses"
			wizard=""
			script="CurrentMap/sequences/seq23.vs">
		</sequence>
		<sequence
			name="AutoPlay"
			wizard=""
			script="CurrentMap/sequences/seq26.vs">
		</sequence>
	</sequences>
