<translationtable>
<translationtableentry text="Landing in Africa - 204 BC" result="Desembarco en África - 204 a.C."/>
<translationtableentry text="Sbarco in Africa - 204 a.C." result="Desembarco en África - 204 a.C."/>
<translationtableentry text="Each victory reaped by Hannibal in the heart of Italy is a further blow to the pride of Rome.\nTo force him to withdraw, the Senate entrusts Scipio with the task of attacking Carthage on its home territory.\nThe Roman general, who defeated the Carthaginians in Hispania, disembarks in North Africa..." result="Cada victoria de Aníbal en el corazón de Italia supone una afrenta al orgullo de Roma.\nPara forzar su retirada, el Senado encomienda a Escipión atacar a Cartago en su propio territorio.\nEl general romano, vencedor de los Cartagineses en Hispania, desembarca en el norte de África..."/>
<translationtableentry text="Ogni vittoria di Annibale all'interno della penisola italica costituisce un affronto all'orgoglio di Roma.\nPer indurlo alla ritirata, il Senato affida a Scipione l'incarico di attaccare l'esercito cartaginese in patria.\nIl generale romano, vincitore dei Cartaginesi in Spagna, sbarca nel nord dell'Africa..." result="Cada victoria de Aníbal en el corazón de Italia supone una afrenta al orgullo de Roma.\nPara forzar su retirada, el Senado encomienda a Escipión atacar a Cartago en su propio territorio.\nEl general romano, vencedor de los Cartagineses en Hispania, desembarca en el norte de África..."/>
<translationtableentry text="Romans" result="Romanos"/>
<translationtableentry text="Romani" result="Romanos"/>
<translationtableentry text="Numidian allies" result="Aliados numidas"/>
<translationtableentry text="Alleati numidi" result="Aliados numidas"/>
<translationtableentry text="Carthaginians" result="Cartagineses"/>
<translationtableentry text="Cartaginesi" result="Cartagineses"/>
<translationtableentry text="Annibale" result="Aníbal"/>
<translationtableentry text="Numidian enemies" result="Enemigos numidas"/>
<translationtableentry text="Nemici numidi" result="Enemigos numidas"/>
<translationtableentry text="Iberians" result="Iberos"/>
<translationtableentry text="Iberi" result="Iberos"/>
<translationtableentry text="Movies/ENG/GreatBattles/1_Intro_Great_B_Zama.avi" result="Movies/SPA/GreatBattles/1_Intro_Great_B_Zama.avi"/>
<translationtableentry text="Movies/ENG/GreatBattles/1_Extro_Great_B_Zama.avi" result="Movies/SPA/GreatBattles/1_Extro_Great_B_Zama.avi"/>
<translationtableentry text="Utica" result="Útica"/>
<translationtableentry text="Masinissa's camp" result="Campamento de Masinisa"/>
<translationtableentry text="Numidian camp" result="Campamento numida"/>
<translationtableentry text="Carthaginian camp" result="Campamento cartaginés"/>
<translationtableentry text="Scipio" result="Escipión"/>
<translationtableentry text="Hannibal Barca" result="Aníbal Barca"/>
<translationtableentry text="Masinissa" result="Masinisa"/>
<translationtableentry text="You have defeated Hannibal at Zama!" result="¡Has derrotado a Aníbal en Zama!"/>
<translationtableentry text="Scipio has died." result="Escipión ha muerto."/>
</translationtable>